kbase_mcp_server/__init__.py
kbase_mcp_server/__main__.py
kbase_mcp_server/server.py
kbase_mcp_server-1.0.8.dist-info/METADATA
kbase_mcp_server-1.0.8.dist-info/WHEEL
kbase_mcp_server-1.0.8.dist-info/entry_points.txt
kbase_mcp_server-1.0.8.dist-info/licenses/LICENSE
kbase_mcp_server-1.0.8.dist-info/RECORD
