Metadata-Version: 2.4
Name: kbase-mcp-server
Version: 1.0.8
Summary: yifangyun doc convert kbase
Author-email: wjx <wjx@gmail.com>
License: MIT
License-File: LICENSE
Classifier: Development Status :: 3 - Alpha
Classifier: Intended Audience :: Developers
Classifier: License :: OSI Approved :: MIT License
Classifier: Programming Language :: Python :: 3
Classifier: Programming Language :: Python :: 3.10
Classifier: Programming Language :: Python :: 3.11
Classifier: Programming Language :: Python :: 3.12
Requires-Python: >=3.10
Requires-Dist: mcp>=1.0.0
Requires-Dist: requests
Requires-Dist: tqdm
